more.signals-0.1.0-py3.6-nspkg.pth
more/signals/__init__.py
more/signals/directives.py
more/signals/main.py
more/signals/tests/__init__.py
more/signals/tests/test_signals.py
more.signals-0.1.0.dist-info/DESCRIPTION.rst
more.signals-0.1.0.dist-info/METADATA
more.signals-0.1.0.dist-info/RECORD
more.signals-0.1.0.dist-info/WHEEL
more.signals-0.1.0.dist-info/metadata.json
more.signals-0.1.0.dist-info/namespace_packages.txt
more.signals-0.1.0.dist-info/top_level.txt
