Metadata-Version: 2.0
Name: more.signals
Version: 0.1.0
Summary: Events for Morepath
Home-page: https://github.com/blaflamme/more.signals
Author: Blaise Laflamme
Author-email: blaise@laflamme.org
License: BSD
Keywords: morepath events signals blinker
Platform: any
Classifier: License :: OSI Approved :: BSD License
Classifier: Programming Language :: Python :: 2
Classifier: Programming Language :: Python :: 2.7
Classifier: Programming Language :: Python :: 3
Classifier: Programming Language :: Python :: 3.5
Classifier: Programming Language :: Python :: 3.6
Requires-Dist: blinker
Requires-Dist: morepath
Provides-Extra: docs
Requires-Dist: docutils; extra == 'docs'
Requires-Dist: sphinx; extra == 'docs'
Provides-Extra: pypi
Requires-Dist: pypandoc; extra == 'pypi'
Requires-Dist: twine; extra == 'pypi'
Provides-Extra: test
Requires-Dist: coverage; extra == 'test'
Requires-Dist: pytest; extra == 'test'
Requires-Dist: pytest-cov; extra == 'test'
Requires-Dist: webtest; extra == 'test'
